crefi
logger
crefi_helper
version
