Metadata-Version: 1.0
Name: crefi
Version: 2.0.4
Summary: A tool to generate different IO's and create files on any mount point
Home-page: https://github.com/vijaykumar-koppad/Crefi
Author: Vijaykumar Koppad
Author-email: vijaykumar.koppad@gmail.com
License: BSD
Platform: UNKNOWN
